[{"name": "\u5927\u5b66\u82f1\u8bed\uff08\u82f1\u8bed\u65b0\u95fb\u9605\u8bfb\uff09", "num": "1", "code": "F08006", "margin": "-261", "url": "http://xk.zucc.edu.cn/clsPage/xsxjs.aspx?xkkh=B13D006745DA6701A711ADDC7C4D83A8ABCC00EA6ACEBC04FFEB13702DE49D8C&xh=31901040", "detail": [{"secondary_num": "1", "code": "(2019-2020-2)-F08006-J07041-2", "teacher": "\u9f9a\u662d", "time": "\u5468\u4e8c\u7b2c1,2\u8282{\u7b2c1-16\u5468}", "margin": "-73/40"}, {"secondary_num": "2", "code": "(2019-2020-2)-F08006-J07041-3", "teacher": "\u9f9a\u662d", "time": "\u5468\u4e8c\u7b2c3,4\u8282{\u7b2c1-16\u5468}", "margin": "-50/40"}, {"secondary_num": "3", "code": "(2019-2020-2)-F08006-J07041-1", "teacher": "\u9f9a\u662d", "time": "\u5468\u4e8c\u7b2c6,7\u8282{\u7b2c1-16\u5468}", "margin": "-41/40"}, {"secondary_num": "4", "code": "(2019-2020-2)-F08006-J09003-1", "teacher": "\u9648\u6653\u8fdc", "time": "\u5468\u4e09\u7b2c1,2\u8282{\u7b2c1-16\u5468}", "margin": "-17/40"}, {"secondary_num": "5", "code": "(2019-2020-2)-F08006-J09003-4", "teacher": "\u9648\u6653\u8fdc", "time": "\u5468\u4e09\u7b2c3,4\u8282{\u7b2c1-16\u5468}", "margin": "-7/40"}, {"secondary_num": "6", "code": "(2019-2020-2)-F08006-J09003-3", "teacher": "\u9648\u6653\u8fdc", "time": "\u5468\u4e09\u7b2c6,7\u8282{\u7b2c1-16\u5468}", "margin": "-5/40"}, {"secondary_num": "7", "code": "(2019-2020-2)-F08006-J07041-4", "teacher": "\u9f9a\u662d", "time": "\u5468\u56db\u7b2c6,7\u8282{\u7b2c1-16\u5468}", "margin": "-46/40"}, {"secondary_num": "8", "code": "(2019-2020-2)-F08006-J09003-2", "teacher": "\u9648\u6653\u8fdc", "time": "\u5468\u4e00\u7b2c1,2\u8282{\u7b2c1-16\u5468}", "margin": "-14/40"}, {"secondary_num": "9", "code": "(2019-2020-2)-F08006-J09003-5", "teacher": "\u9648\u6653\u8fdc", "time": "\u5468\u4e00\u7b2c6,7\u8282{\u7b2c1-16\u5468}", "margin": "-8/40"}]},{"name": "\u5927\u5b66\u82f1\u8bed\uff08\u5b9e\u7528\u7ffb\u8bd1\uff09", "num": "2", "code": "F08010", "margin": "-27", "url": "http://xk.zucc.edu.cn/clsPage/xsxjs.aspx?xkkh=B13D006745DA6701A711ADDC7C4D83A88574208877A9B02D277BFC36D3EE8993&xh=31901040", "detail": [{"secondary_num": "1", "code": "(2019-2020-2)-F08010-J08048-2", "teacher": "\u8a79\u5a77", "time": "\u5468\u4e09\u7b2c3,4\u8282{\u7b2c1-16\u5468}", "margin": "-11/40"}, {"secondary_num": "2", "code": "(2019-2020-2)-F08010-J08048-5", "teacher": "\u8a79\u5a77", "time": "\u5468\u4e09\u7b2c6,7\u8282{\u7b2c1-16\u5468}", "margin": "-2/40"}, {"secondary_num": "3", "code": "(2019-2020-2)-F08010-J08048-4", "teacher": "\u8a79\u5a77", "time": "\u5468\u4e00\u7b2c1,2\u8282{\u7b2c1-16\u5468}", "margin": "-9/40"}, {"secondary_num": "4", "code": "(2019-2020-2)-F08010-J08048-3", "teacher": "\u8a79\u5a77", "time": "\u5468\u4e00\u7b2c3,4\u8282{\u7b2c1-16\u5468}", "margin": "-1/40"}, {"secondary_num": "5", "code": "(2019-2020-2)-F08010-J08048-1", "teacher": "\u8a79\u5a77", "time": "\u5468\u4e00\u7b2c6,7\u8282{\u7b2c1-16\u5468}", "margin": "-4/40"}]},{"name": "\u5927\u5b66\u82f1\u8bed\uff08\u56fd\u9645\u4ea4\u6d41\u82f1\u8bed\u89c6\u542c\u8bf4\uff09", "num": "3", "code": "F08003", "margin": "283", "url": "http://xk.zucc.edu.cn/clsPage/xsxjs.aspx?xkkh=B13D006745DA6701A711ADDC7C4D83A8A05EC5C9CE651D0EFDEDA4915488F895&xh=31901040", "detail": [{"secondary_num": "1", "code": "(2019-2020-2)-F08003-J03079-4", "teacher": "\u674e\u5360\u7ea2", "time": "\u5468\u4e8c\u7b2c3,4\u8282{\u7b2c1-16\u5468}", "margin": "30/40"}, {"secondary_num": "2", "code": "(2019-2020-2)-F08003-J03079-3", "teacher": "\u674e\u5360\u7ea2", "time": "\u5468\u4e8c\u7b2c6,7\u8282{\u7b2c1-16\u5468}", "margin": "24/40"}, {"secondary_num": "3", "code": "(2019-2020-2)-F08003-C11004-3", "teacher": "\u6731\u6f47\u6f47", "time": "\u5468\u4e09\u7b2c1,2\u8282{\u7b2c1-16\u5468}", "margin": "32/40"}, {"secondary_num": "4", "code": "(2019-2020-2)-F08003-C11004-5", "teacher": "\u6731\u6f47\u6f47", "time": "\u5468\u4e09\u7b2c3,4\u8282{\u7b2c1-16\u5468}", "margin": "25/40"}, {"secondary_num": "5", "code": "(2019-2020-2)-F08003-C11004-1", "teacher": "\u6731\u6f47\u6f47", "time": "\u5468\u4e09\u7b2c6,7\u8282{\u7b2c1-16\u5468}", "margin": "35/40"}, {"secondary_num": "6", "code": "(2019-2020-2)-F08003-J03079-5", "teacher": "\u674e\u5360\u7ea2", "time": "\u5468\u56db\u7b2c1,2\u8282{\u7b2c1-16\u5468}", "margin": "14/40"}, {"secondary_num": "7", "code": "(2019-2020-2)-F08003-J03079-1", "teacher": "\u674e\u5360\u7ea2", "time": "\u5468\u56db\u7b2c3,4\u8282{\u7b2c1-16\u5468}", "margin": "34/40"}, {"secondary_num": "8", "code": "(2019-2020-2)-F08003-J03079-2", "teacher": "\u674e\u5360\u7ea2", "time": "\u5468\u56db\u7b2c6,7\u8282{\u7b2c1-16\u5468}", "margin": "23/40"}, {"secondary_num": "9", "code": "(2019-2020-2)-F08003-C11004-2", "teacher": "\u6731\u6f47\u6f47", "time": "\u5468\u4e00\u7b2c1,2\u8282{\u7b2c1-16\u5468}", "margin": "32/40"}, {"secondary_num": "10", "code": "(2019-2020-2)-F08003-C11004-4", "teacher": "\u6731\u6f47\u6f47", "time": "\u5468\u4e00\u7b2c3,4\u8282{\u7b2c1-16\u5468}", "margin": "34/40"}]},{"name": "\u5927\u5b66\u82f1\u8bed\uff08\u5b66\u672f\u82f1\u8bed\u8bfb\u5199\uff09", "num": "4", "code": "F08002", "margin": "23", "url": "http://xk.zucc.edu.cn/clsPage/xsxjs.aspx?xkkh=B13D006745DA6701A711ADDC7C4D83A86B1151EA6A41AE2A7401A8B46CB36DCA&xh=31901040", "detail": [{"secondary_num": "1", "code": "(2019-2020-2)-F08002-J03041-2", "teacher": "\u5434\u8587\u8587", "time": "\u5468\u4e8c\u7b2c1,2\u8282{\u7b2c1-16\u5468}", "margin": "-2/40"}, {"secondary_num": "2", "code": "(2019-2020-2)-F08002-J03041-1", "teacher": "\u5434\u8587\u8587", "time": "\u5468\u4e8c\u7b2c3,4\u8282{\u7b2c1-16\u5468}", "margin": "25/40"}]},{"name": "\u5927\u5b66\u82f1\u8bed\uff08\u5b66\u672f\u82f1\u8bed\u542c\u8bf4\uff09", "num": "5", "code": "F08001", "margin": "32", "url": "http://xk.zucc.edu.cn/clsPage/xsxjs.aspx?xkkh=B13D006745DA6701A711ADDC7C4D83A8AE0869AC7F128F053B7DA3CCC34D2395&xh=31901040", "detail": [{"secondary_num": "1", "code": "(2019-2020-2)-F08001-C14008-1", "teacher": "\u5f20\u5b87", "time": "\u5468\u4e09\u7b2c1,2\u8282{\u7b2c1-16\u5468}", "margin": "15/40"}, {"secondary_num": "2", "code": "(2019-2020-2)-F08001-C14008-2", "teacher": "\u5f20\u5b87", "time": "\u5468\u4e09\u7b2c3,4\u8282{\u7b2c1-16\u5468}", "margin": "17/40"}]},{"name": "\u5927\u5b66\u82f1\u8bed\uff08\u82f1\u8bed\u6f14\u8bb2\u8fdb\u9636-\u8bf4\u670d\u4e0e\u601d\u8fa8\uff09", "num": "6", "code": "F08005", "margin": "177", "url": "http://xk.zucc.edu.cn/clsPage/xsxjs.aspx?xkkh=B13D006745DA6701A711ADDC7C4D83A8E92B49C55645990DC635E8971270BFD7&xh=31901040", "detail": [{"secondary_num": "1", "code": "(2019-2020-2)-F08005-J08043-2", "teacher": "\u6768\u6d01\u7fbd", "time": "\u5468\u4e8c\u7b2c1,2\u8282{\u7b2c1-16\u5468}", "margin": "34/40"}, {"secondary_num": "2", "code": "(2019-2020-2)-F08005-J08043-1", "teacher": "\u6768\u6d01\u7fbd", "time": "\u5468\u4e8c\u7b2c3,4\u8282{\u7b2c1-16\u5468}", "margin": "37/40"}, {"secondary_num": "3", "code": "(2019-2020-2)-F08005-J03113-3", "teacher": "\u6d2a\u4e00\u9e23", "time": "\u5468\u4e00\u7b2c1,2\u8282{\u7b2c1-16\u5468}", "margin": "33/40"}, {"secondary_num": "4", "code": "(2019-2020-2)-F08005-J03113-2", "teacher": "\u6d2a\u4e00\u9e23", "time": "\u5468\u4e00\u7b2c3,4\u8282{\u7b2c1-16\u5468}", "margin": "36/40"}, {"secondary_num": "5", "code": "(2019-2020-2)-F08005-J03113-1", "teacher": "\u6d2a\u4e00\u9e23", "time": "\u5468\u4e00\u7b2c6,7\u8282{\u7b2c1-16\u5468}", "margin": "37/40"}]},{"name": "\u5927\u5b66\u82f1\u8bed\uff08\u82f1\u8bed\u6f14\u8bb2\u5165\u95e8-\u6280\u5de7\u4e0e\u5b9e\u8df5\uff09", "num": "7", "code": "F08004", "margin": "139", "url": "http://xk.zucc.edu.cn/clsPage/xsxjs.aspx?xkkh=B13D006745DA6701A711ADDC7C4D83A88F589E1BE440C45F8D451CFE54605D78&xh=31901040", "detail": [{"secondary_num": "1", "code": "(2019-2020-2)-F08004-J08043-1", "teacher": "\u6768\u6d01\u7fbd", "time": "\u5468\u4e8c\u7b2c6,7\u8282{\u7b2c1-16\u5468}", "margin": "23/40"}, {"secondary_num": "2", "code": "(2019-2020-2)-F08004-J03113-2", "teacher": "\u6d2a\u4e00\u9e23", "time": "\u5468\u4e09\u7b2c1,2\u8282{\u7b2c1-16\u5468}", "margin": "30/40"}, {"secondary_num": "3", "code": "(2019-2020-2)-F08004-J03113-1", "teacher": "\u6d2a\u4e00\u9e23", "time": "\u5468\u4e09\u7b2c3,4\u8282{\u7b2c1-16\u5468}", "margin": "35/40"}, {"secondary_num": "4", "code": "(2019-2020-2)-F08004-J08043-2", "teacher": "\u6768\u6d01\u7fbd", "time": "\u5468\u56db\u7b2c1,2\u8282{\u7b2c1-16\u5468}", "margin": "20/40"}, {"secondary_num": "5", "code": "(2019-2020-2)-F08004-J08043-3", "teacher": "\u6768\u6d01\u7fbd", "time": "\u5468\u56db\u7b2c3,4\u8282{\u7b2c1-16\u5468}", "margin": "31/40"}]},{"name": "\u5927\u5b66\u5916\u8bed\uff08\u65e5\u8bed\u57fa\u7840\u4e0e\u65e5\u672c\u6587\u5316\uff09", "num": "8", "code": "F08012", "margin": "-186", "url": "http://xk.zucc.edu.cn/clsPage/xsxjs.aspx?xkkh=B13D006745DA6701A711ADDC7C4D83A8697BABEBAA6325D4B35BB9B72BD3EEA6&xh=31901040", "detail": [{"secondary_num": "1", "code": "(2019-2020-2)-F08012-J08027-1", "teacher": "\u9648\u745e\u82f1", "time": "\u5468\u4e00\u7b2c3,4\u8282{\u7b2c1-16\u5468}", "margin": "-64/40"}, {"secondary_num": "2", "code": "(2019-2020-2)-F08012-J08027-2", "teacher": "\u9648\u745e\u82f1", "time": "\u5468\u4e00\u7b2c6,7\u8282{\u7b2c1-16\u5468}", "margin": "-122/40"}]},{"name": "\u5927\u5b66\u82f1\u8bed\uff08\u5b9e\u7528\u53e3\u8bed\uff09", "num": "9", "code": "F08007", "margin": "-244", "url": "http://xk.zucc.edu.cn/clsPage/xsxjs.aspx?xkkh=B13D006745DA6701A711ADDC7C4D83A87935513FE74A13F0D9777C75545D0B85&xh=31901040", "detail": [{"secondary_num": "1", "code": "(2019-2020-2)-F08007-J02106-3", "teacher": "\u9648\u6653\u89d2", "time": "\u5468\u4e8c\u7b2c3,4\u8282{\u7b2c1-16\u5468}", "margin": "-29/40"}, {"secondary_num": "2", "code": "(2019-2020-2)-F08007-J02106-2", "teacher": "\u9648\u6653\u89d2", "time": "\u5468\u4e8c\u7b2c6,7\u8282{\u7b2c1-16\u5468}", "margin": "-8/40"}, {"secondary_num": "3", "code": "(2019-2020-2)-F08007-C10450-3", "teacher": "NATHAN ROBERT EPLEY", "time": "\u5468\u4e09\u7b2c1,2\u8282{\u7b2c1-16\u5468}", "margin": "-62/40"}, {"secondary_num": "4", "code": "(2019-2020-2)-F08007-C10450-1", "teacher": "NATHAN ROBERT EPLEY", "time": "\u5468\u4e09\u7b2c6,7\u8282{\u7b2c1-16\u5468}", "margin": "-22/40"}, {"secondary_num": "5", "code": "(2019-2020-2)-F08007-J02106-5", "teacher": "\u9648\u6653\u89d2", "time": "\u5468\u56db\u7b2c1,2\u8282{\u7b2c1-16\u5468}", "margin": "-36/40"}, {"secondary_num": "6", "code": "(2019-2020-2)-F08007-J02106-4", "teacher": "\u9648\u6653\u89d2", "time": "\u5468\u56db\u7b2c3,4\u8282{\u7b2c1-16\u5468}", "margin": "-6/40"}, {"secondary_num": "7", "code": "(2019-2020-2)-F08007-J02106-1", "teacher": "\u9648\u6653\u89d2", "time": "\u5468\u56db\u7b2c6,7\u8282{\u7b2c1-16\u5468}", "margin": "-15/40"}, {"secondary_num": "8", "code": "(2019-2020-2)-F08007-C10450-2", "teacher": "NATHAN ROBERT EPLEY", "time": "\u5468\u4e00\u7b2c1,2\u8282{\u7b2c1-16\u5468}", "margin": "-66/40"}]},{"name": "\u5927\u5b66\u82f1\u8bed\uff08\u96c5\u601d\u82f1\u8bed\uff09", "num": "10", "code": "F08009", "margin": "131", "url": "http://xk.zucc.edu.cn/clsPage/xsxjs.aspx?xkkh=B13D006745DA6701A711ADDC7C4D83A88549AFF70146A4BDBA4784F61B5302CF&xh=31901040", "detail": [{"secondary_num": "1", "code": "(2019-2020-2)-F08009-J03083-1", "teacher": "\u5f90\u5b81\u71d5", "time": "\u5468\u4e8c\u7b2c1,2\u8282{\u7b2c1-16\u5468}", "margin": "27/40"}, {"secondary_num": "2", "code": "(2019-2020-2)-F08009-J03083-3", "teacher": "\u5f90\u5b81\u71d5", "time": "\u5468\u4e8c\u7b2c3,4\u8282{\u7b2c1-16\u5468}", "margin": "24/40"}, {"secondary_num": "3", "code": "(2019-2020-2)-F08009-J03083-4", "teacher": "\u5f90\u5b81\u71d5", "time": "\u5468\u4e8c\u7b2c6,7\u8282{\u7b2c1-16\u5468}", "margin": "31/40"}, {"secondary_num": "4", "code": "(2019-2020-2)-F08009-J03083-2", "teacher": "\u5f90\u5b81\u71d5", "time": "\u5468\u56db\u7b2c3,4\u8282{\u7b2c1-16\u5468}", "margin": "27/40"}, {"secondary_num": "5", "code": "(2019-2020-2)-F08009-J03083-5", "teacher": "\u5f90\u5b81\u71d5", "time": "\u5468\u56db\u7b2c6,7\u8282{\u7b2c1-16\u5468}", "margin": "22/40"}]}]